bull_stack/__init__.py
bull_stack/migrate.py
bull_stack-0.0.8.dist-info/licenses/LICENSE
bull_stack-0.0.8.dist-info/METADATA
bull_stack-0.0.8.dist-info/WHEEL
bull_stack-0.0.8.dist-info/top_level.txt
bull_stack-0.0.8.dist-info/RECORD
