Metadata-Version: 2.4
Name: Bull-Stack
Version: 0.0.8
License-File: LICENSE
Requires-Dist: Flask-SQLAlchemy
Requires-Dist: Flask-Migrate
Requires-Dist: Flask-FEFset
Requires-Dist: Flask-UXFab
Requires-Dist: Flask-Bauto
Requires-Dist: Flask-IAM
Provides-Extra: dev
Requires-Dist: build; extra == "dev"
Requires-Dist: twine; extra == "dev"
Dynamic: license-file
